sopel_modules.sports-2.2.4-py3.9-nspkg.pth
sopel_modules/sports/__init__.py
sopel_modules/sports/mlb.py
sopel_modules/sports/nfl.py
sopel_modules/sports/nhl.py
sopel_modules_sports-2.2.4.dist-info/licenses/LICENSE
sopel_modules_sports-2.2.4.dist-info/METADATA
sopel_modules_sports-2.2.4.dist-info/WHEEL
sopel_modules_sports-2.2.4.dist-info/namespace_packages.txt
sopel_modules_sports-2.2.4.dist-info/top_level.txt
sopel_modules_sports-2.2.4.dist-info/RECORD
