Metadata-Version: 2.4
Name: sopel_modules.sports
Version: 2.2.4
Summary: Sopel Sports Module
Home-page: http://github.com/rustybower/sopel-sports
Author: Rusty Bower
Author-email: rusty@rustybower.com
License: MIT License
License-File: LICENSE
Requires-Dist: python-dateutil
Requires-Dist: pytz
Requires-Dist: requests
Requires-Dist: sopel
Dynamic: author
Dynamic: author-email
Dynamic: description
Dynamic: description-content-type
Dynamic: home-page
Dynamic: license
Dynamic: license-file
Dynamic: requires-dist
Dynamic: summary
